secdefender.py
secdefender-0.1.0.dist-info/METADATA
secdefender-0.1.0.dist-info/WHEEL
secdefender-0.1.0.dist-info/entry_points.txt
secdefender-0.1.0.dist-info/top_level.txt
secdefender-0.1.0.dist-info/RECORD
